Metadata-Version: 1.1
Name: zunda-python
Version: 0.1.3
Summary: Zunda: Japanese Enhanced Modality Analyzer client for Python
Home-page: https://github.com/ikegami-yukino/zunda-python
Author: Yukino Ikegami
Author-email: yknikgm@gmail.com
License: MIT License
Keywords: modality analyzer
Platform: POSIX
Platform: Unix
Platform: MacOS
Classifier: Development Status :: 3 - Alpha
Classifier: Intended Audience :: Developers
Classifier: Intended Audience :: Information Technology
Classifier: Intended Audience :: Science/Research
Classifier: License :: OSI Approved :: MIT License
Classifier: Natural Language :: Japanese
Classifier: Programming Language :: Python :: 3.3
Classifier: Programming Language :: Python :: 3.4
Classifier: Programming Language :: Python :: 3.5
Classifier: Programming Language :: Python :: 3.6
Classifier: Programming Language :: Python :: 3.7
Classifier: Topic :: Text Processing :: Linguistic
